pysophy/__init__.py
pysophy/core.py
pysophy-0.1.0.dist-info/licenses/LICENCE
pysophy-0.1.0.dist-info/METADATA
pysophy-0.1.0.dist-info/WHEEL
pysophy-0.1.0.dist-info/top_level.txt
pysophy-0.1.0.dist-info/RECORD
