Metadata-Version: 2.4
Name: pysophy
Version: 0.1.0
Summary: A knowledge processing library
Author-email: Your Name <you@example.com>
License: MIT
License-File: LICENCE
Dynamic: license-file
